esm.cpython-311-darwin.so
esmre.py
esmre-1.0.1.dist-info/AUTHORS
esmre-1.0.1.dist-info/COPYING
esmre-1.0.1.dist-info/METADATA
esmre-1.0.1.dist-info/WHEEL
esmre-1.0.1.dist-info/top_level.txt
esmre-1.0.1.dist-info/RECORD
