Metadata-Version: 2.1
Name: esmre
Version: 1.0.1
Summary: Regular expression accelerator
Home-page: https://github.com/wharris/esmre
Author: Will Harris
Author-email: esmre@greatlibrary.net
License: GNU LGPL
Platform: POSIX
Classifier: Development Status :: 5 - Production/Stable
Classifier: Intended Audience :: Developers
Classifier: License :: OSI Approved :: GNU Library or Lesser General Public License (LGPL)
Classifier: Operating System :: POSIX
Classifier: Programming Language :: C
Classifier: Programming Language :: Cython
Classifier: Programming Language :: Python
Classifier: Topic :: Software Development :: Libraries :: Python Modules
Classifier: Topic :: Text Processing :: Indexing
License-File: COPYING
License-File: AUTHORS
Requires-Dist: setuptools
